strapi_mcp_server/__main__.py
mm_strapi_mcp-0.1.0.dist-info/METADATA
mm_strapi_mcp-0.1.0.dist-info/WHEEL
mm_strapi_mcp-0.1.0.dist-info/entry_points.txt
mm_strapi_mcp-0.1.0.dist-info/top_level.txt
mm_strapi_mcp-0.1.0.dist-info/RECORD
