Metadata-Version: 2.4
Name: mm-strapi-mcp
Version: 0.1.0
Summary: An MCP server for interacting with Strapi CMS.
Author-email: rikutoe <rikuto@magicmoment.jp>
Project-URL: Homepage, https://github.com/mm-gtm/mm-strapi-mcp
Project-URL: Bug Tracker, https://github.com/mm-gtm/mm-strapi-mcp/issues
Classifier: Programming Language :: Python :: 3
Classifier: License :: OSI Approved :: MIT License
Classifier: Operating System :: OS Independent
Requires-Python: >=3.8
Requires-Dist: requests
Requires-Dist: Pillow
Requires-Dist: python-multipart
Requires-Dist: fastmcp
